{
  "todos": [
    {
      "text": "0",
      "done": false,
      "id": 1
    },
    {
      "text": "1",
      "done": false,
      "id": 2
    },
    {
      "text": "todos 추가",
      "done": false,
      "id": 3
    }
  ],
  "memos": [
    {
      "x": 0,
      "y": 0,
      "w": 2,
      "h": 2,
      "i": "0",
      "text": "가나다라마바사\\n\\n아자차카"
    },
    { "x": 2, "y": 0, "w": 2, "h": 4, "i": "1", "text": "할일\\n\\n아자차카" },
    {
      "x": 4,
      "y": 0,
      "w": 2,
      "h": 5,
      "i": "2",
      "text": "2222222222\\n\\n222222222222222"
    }
  ]
}
